[
    {
        "id": 1,
        "nome": "Ana Catarina",
        "especialidade": "Dermatologista",
        "planos": "Unimed",
        "preco": "220"
    },
    {
        "id": 2,
        "nome": "Ricardo Silvano",
        "especialidade": "Pneumologista",
        "planos": "Bradesco e Unimed",
        "preco": 350
    },
    {
        "id": 3,
        "nome": "J\u00falia Caldas",
        "especialidade": "Cardiologista",
        "planos": "Bradesco, Unimed e VidaLeve",
        "preco": 250
    },
    {
        "id": 4,
        "nome": "Rafael Lopes",
        "especialidade": "Neurologista",
        "planos": "Apenas particular",
        "preco": 350
    },
    {
        "id": 5,
        "nome": "Maria Pereira",
        "especialidade": "Pediatra",
        "planos": "Unimed",
        "preco": 250
    },
    {
        "id": 6,
        "nome": "Bruna Soares",
        "especialidade": "Ginecologista",
        "planos": "Bradesco e Unimed",
        "preco": 300
    },
    {
        "id": 7,
        "nome": "Thiago Ramos",
        "especialidade": "Oftalmologista",
        "planos": "Unimed",
        "preco": "300"
    }
]